Workbook

Sheet 🏠 Início
B2: CENTRAL TATTOO
B3: SISTEMA COMPLETO DE GESTÃO PARA ESTÚDIOS DE TATUAGEM
B7: 📊 | D7: 📅 | F7: 👥 | H7: 💰 | J7: 🧮 | L7: 📦 | N7: 🎯 | P7: 📈
B8: DASHBOARD | D8: AGENDA | F8: CLIENTES | H8: FINANCEIRO | J8: CALCULADORA | L8: ESTOQUE | N8: LEADS | P8: METAS
B9: Visão geral do negócio | D9: Agendamentos e sessões | F9: CRM e fidelização | H9: Receitas e despesas | J9: Precificação premium | L9: Materiais e reposição | N9: Pipeline de vendas | P9: Objetivos e previsões
B12: ✅ COMO USAR O SISTEMA
B13: 1. | D13: Comece preenchendo seus dados na aba FINANCEIRO → Configure receitas e despesas mensais
B14: 2. | D14: Cadastre seus clientes na aba CLIENTES → Preencha nome, contato e histórico de tattoos
B15: 3. | D15: Use a CALCULADORA para precificar corretamente cada projeto sem perder margem
B16: 4. | D16: Acompanhe a AGENDA diariamente para controlar sessões e evitar conflitos
B17: 5. | D17: Registre todos os LEADS no pipeline para nenhuma oportunidade se perder
B18: 6. | D18: Monitore o DASHBOARD semanalmente para tomar decisões com dados reais
B19: 7. | D19: Use as METAS para definir objetivos mensais e acompanhar o crescimento
B20: 8. | D20: Controle o ESTOQUE para evitar falta de material durante as sessões
B22: 💎 Central Tattoo — Sistema Premium de Gestão para Tatuadores | Versão 2026

Sheet 📊 Dashboard
B2: 📊 DASHBOARD — CENTRAL TATTOO
B3: =TEXT(TODAY(),"MMMM \ YYYY")
B5: 💰 FATURAMENTO MES | G5: 📉 DESPESAS MES | L5: 💎 LUCRO LIQUIDO | Q5: 🎯 SESSOES MES | V5: 👥 CLIENTES NOVOS
B6: =SUMIF(Financeiro!C:C,"Receita",Financeiro!D:D) | G6: =SUMIF(Financeiro!C:C,"Despesa",Financeiro!D:D) | L6: =B6-G6 | Q6: =COUNTA(Agenda!B:B)-1 | V6: =COUNTIF(Clientes!G:G,"Novo")
B10: 🎫 TICKET MEDIO | G10: 📊 MARGEM LUCRO | L10: ❌ CANCELAMENTOS | Q10: ⭐ CLIENTES FIDELIZ. | V10: 📦 VALOR ESTOQUE
B11: =IFERROR(B6/Q6,0) | G11: =IFERROR(L6/B6,0) | L11: =COUNTIF(Agenda!F:F,"Cancelado") | Q11: =COUNTIF(Clientes!G:G,"Fidelizado") | V11: =SUMPRODUCT(Estoque!C2:C100,Estoque!D2:D100)
B15: 📅 PRÓXIMAS SESSÕES | M15: 🎯 METAS DO MÊS
B16: Data | C16: Hora | D16: Cliente | E16: Estilo | F16: Valor | G16: Status
M17: Faturamento Alvo | R17: R$ 8.000 | V17: Atualizar
M19: Sessões Alvo | R19: 20 | V19: Atualizar
M21: Novos Clientes | R21: 5 | V21: Atualizar
M23: Ticket Médio Alvo | R23: R$ 400 | V23: Atualizar

Sheet 📅 Agenda
B2: 📅 AGENDA DE SESSÕES — CENTRAL TATTOO
B4: DATA | C4: HORA | D4: CLIENTE | E4: TELEFONE | F4: ESTILO | G4: STATUS | H4: VALOR (R$) | I4: =IF(G4<>"",G4-H4,"") | J4: SALDO (R$) | K4: DURAÇÃO | L4: LOCAL | M4: OBS
I5: =IF(G5<>"",G5-H5,"")
I6: =IF(G6<>"",G6-H6,"")
I7: =IF(G7<>"",G7-H7,"")
I8: =IF(G8<>"",G8-H8,"")
I9: =IF(G9<>"",G9-H9,"")
I10: =IF(G10<>"",G10-H10,"")
I11: =IF(G11<>"",G11-H11,"")
I12: =IF(G12<>"",G12-H12,"")
I13: =IF(G13<>"",G13-H13,"")
I14: =IF(G14<>"",G14-H14,"")
I15: =IF(G15<>"",G15-H15,"")
I16: =IF(G16<>"",G16-H16,"")
... I105: =IF(G105<>"",G105-H105,"")
B106: TOTAIS DO MÊS | G106: =SUM(G5:G105) | H106: =SUM(H5:H105) | I106: =IF(G106<>"",G106-H106,"")
I107: =IF(G107<>"",G107-H107,"")
I108: =IF(G108<>"",G108-H108,"")
I109: =IF(G109<>"",G109-H109,"")
I110: =IF(G110<>"",G110-H110,"")
I111: =IF(G111<>"",G111-H111,"")
I112: =IF(G112<>"",G112-H112,"")
I113: =IF(G113<>"",G113-H113,"")
I114: =IF(G114<>"",G114-H114,"")
I115: =IF(G115<>"",G115-H115,"")
I116: =IF(G116<>"",G116-H116,"")
I117: =IF(G117<>"",G117-H117,"")
I118: =IF(G118<>"",G118-H118,"")
... I400: =IF(G400<>"",G400-H400,"")

Sheet 👥 Clientes CRM
B2: 👥 CRM DE CLIENTES — CENTRAL TATTOO
N3: TICKET MÉDIO | O3: NPS (0-10) | P3: INSTAGRAM | Q3: ORIGEM | R3: ANIVERSÁRIO
B4: NOME | C4: TELEFONE | D4: EMAIL | E4: DATA NASC. | F4: CIDADE | G4: TATTOOS FEITAS | H4: STATUS | I4: ÚLTIMO CONTATO | J4: PRÓX. RETORNO | K4: ESTILO PREF. | L4: INDICADO POR | M4: TOTAL GASTO (R$) | N4: =IF(AND(L4<>"",F4>0),L4/F4,"") | R4: =IF(D4<>"",IF(MONTH(D4)=MONTH(TODAY()),"🎂 Este mês!",""),"")
N5: =IF(AND(L5<>"",F5>0),L5/F5,"") | R5: =IF(D5<>"",IF(MONTH(D5)=MONTH(TODAY()),"🎂 Este mês!",""),"")
N6: =IF(AND(L6<>"",F6>0),L6/F6,"") | R6: =IF(D6<>"",IF(MONTH(D6)=MONTH(TODAY()),"🎂 Este mês!",""),"")
N7: =IF(AND(L7<>"",F7>0),L7/F7,"") | R7: =IF(D7<>"",IF(MONTH(D7)=MONTH(TODAY()),"🎂 Este mês!",""),"")
N8: =IF(AND(L8<>"",F8>0),L8/F8,"") | R8: =IF(D8<>"",IF(MONTH(D8)=MONTH(TODAY()),"🎂 Este mês!",""),"")
N9: =IF(AND(L9<>"",F9>0),L9/F9,"") | R9: =IF(D9<>"",IF(MONTH(D9)=MONTH(TODAY()),"🎂 Este mês!",""),"")
N10: =IF(AND(L10<>"",F10>0),L10/F10,"") | R10: =IF(D10<>"",IF(MONTH(D10)=MONTH(TODAY()),"🎂 Este mês!",""),"")
N11: =IF(AND(L11<>"",F11>0),L11/F11,"") | R11: =IF(D11<>"",IF(MONTH(D11)=MONTH(TODAY()),"🎂 Este mês!",""),"")
N12: =IF(AND(L12<>"",F12>0),L12/F12,"") | R12: =IF(D12<>"",IF(MONTH(D12)=MONTH(TODAY()),"🎂 Este mês!",""),"")
N13: =IF(AND(L13<>"",F13>0),L13/F13,"") | R13: =IF(D13<>"",IF(MONTH(D13)=MONTH(TODAY()),"🎂 Este mês!",""),"")
N14: =IF(AND(L14<>"",F14>0),L14/F14,"") | R14: =IF(D14<>"",IF(MONTH(D14)=MONTH(TODAY()),"🎂 Este mês!",""),"")
N15: =IF(AND(L15<>"",F15>0),L15/F15,"") | R15: =IF(D15<>"",IF(MONTH(D15)=MONTH(TODAY()),"🎂 Este mês!",""),"")
N16: =IF(AND(L16<>"",F16>0),L16/F16,"") | R16: =IF(D16<>"",IF(MONTH(D16)=MONTH(TODAY()),"🎂 Este mês!",""),"")
... N400: =IF(AND(L400<>"",F400>0),L400/F400,"") | R400: =IF(D400<>"",IF(MONTH(D400)=MONTH(TODAY()),"🎂 Este mês!",""),"")

Sheet 🔔 Follow-Up
B2: 🔔 FOLLOW-UP AUTOMÁTICO — ALERTAS DE RETORNO
B4: CLIENTE | C4: TELEFONE | D4: DATA ÚLTIMA TATTOO | E4: DIAS PASSADOS | F4: ALERTA | G4: AÇÃO SUGERIDA | H4: STATUS
E5: =IF(D5<>"",TODAY()-D5,"") | F5: =IF(E5="","",IF(E5>90,"🔴 ENTRAR EM CONTATO",IF(E5>60,"🟡 VERIFICAR EM BREVE","🟢 OK"))) | G5: =IF(E5>90,"Enviar mensagem no WhatsApp com oferta especial",IF(E5>60,"Perguntar sobre nova ideia de tattoo","Aguardar"))
E6: =IF(D6<>"",TODAY()-D6,"") | F6: =IF(E6="","",IF(E6>90,"🔴 ENTRAR EM CONTATO",IF(E6>60,"🟡 VERIFICAR EM BREVE","🟢 OK"))) | G6: =IF(E6>90,"Enviar mensagem no WhatsApp com oferta especial",IF(E6>60,"Perguntar sobre nova ideia de tattoo","Aguardar"))
E7: =IF(D7<>"",TODAY()-D7,"") | F7: =IF(E7="","",IF(E7>90,"🔴 ENTRAR EM CONTATO",IF(E7>60,"🟡 VERIFICAR EM BREVE","🟢 OK"))) | G7: =IF(E7>90,"Enviar mensagem no WhatsApp com oferta especial",IF(E7>60,"Perguntar sobre nova ideia de tattoo","Aguardar"))
E8: =IF(D8<>"",TODAY()-D8,"") | F8: =IF(E8="","",IF(E8>90,"🔴 ENTRAR EM CONTATO",IF(E8>60,"🟡 VERIFICAR EM BREVE","🟢 OK"))) | G8: =IF(E8>90,"Enviar mensagem no WhatsApp com oferta especial",IF(E8>60,"Perguntar sobre nova ideia de tattoo","Aguardar"))
E9: =IF(D9<>"",TODAY()-D9,"") | F9: =IF(E9="","",IF(E9>90,"🔴 ENTRAR EM CONTATO",IF(E9>60,"🟡 VERIFICAR EM BREVE","🟢 OK"))) | G9: =IF(E9>90,"Enviar mensagem no WhatsApp com oferta especial",IF(E9>60,"Perguntar sobre nova ideia de tattoo","Aguardar"))
E10: =IF(D10<>"",TODAY()-D10,"") | F10: =IF(E10="","",IF(E10>90,"🔴 ENTRAR EM CONTATO",IF(E10>60,"🟡 VERIFICAR EM BREVE","🟢 OK"))) | G10: =IF(E10>90,"Enviar mensagem no WhatsApp com oferta especial",IF(E10>60,"Perguntar sobre nova ideia de tattoo","Aguardar"))
E11: =IF(D11<>"",TODAY()-D11,"") | F11: =IF(E11="","",IF(E11>90,"🔴 ENTRAR EM CONTATO",IF(E11>60,"🟡 VERIFICAR EM BREVE","🟢 OK"))) | G11: =IF(E11>90,"Enviar mensagem no WhatsApp com oferta especial",IF(E11>60,"Perguntar sobre nova ideia de tattoo","Aguardar"))
E12: =IF(D12<>"",TODAY()-D12,"") | F12: =IF(E12="","",IF(E12>90,"🔴 ENTRAR EM CONTATO",IF(E12>60,"🟡 VERIFICAR EM BREVE","🟢 OK"))) | G12: =IF(E12>90,"Enviar mensagem no WhatsApp com oferta especial",IF(E12>60,"Perguntar sobre nova ideia de tattoo","Aguardar"))
E13: =IF(D13<>"",TODAY()-D13,"") | F13: =IF(E13="","",IF(E13>90,"🔴 ENTRAR EM CONTATO",IF(E13>60,"🟡 VERIFICAR EM BREVE","🟢 OK"))) | G13: =IF(E13>90,"Enviar mensagem no WhatsApp com oferta especial",IF(E13>60,"Perguntar sobre nova ideia de tattoo","Aguardar"))
E14: =IF(D14<>"",TODAY()-D14,"") | F14: =IF(E14="","",IF(E14>90,"🔴 ENTRAR EM CONTATO",IF(E14>60,"🟡 VERIFICAR EM BREVE","🟢 OK"))) | G14: =IF(E14>90,"Enviar mensagem no WhatsApp com oferta especial",IF(E14>60,"Perguntar sobre nova ideia de tattoo","Aguardar"))
E15: =IF(D15<>"",TODAY()-D15,"") | F15: =IF(E15="","",IF(E15>90,"🔴 ENTRAR EM CONTATO",IF(E15>60,"🟡 VERIFICAR EM BREVE","🟢 OK"))) | G15: =IF(E15>90,"Enviar mensagem no WhatsApp com oferta especial",IF(E15>60,"Perguntar sobre nova ideia de tattoo","Aguardar"))
E16: =IF(D16<>"",TODAY()-D16,"") | F16: =IF(E16="","",IF(E16>90,"🔴 ENTRAR EM CONTATO",IF(E16>60,"🟡 VERIFICAR EM BREVE","🟢 OK"))) | G16: =IF(E16>90,"Enviar mensagem no WhatsApp com oferta especial",IF(E16>60,"Perguntar sobre nova ideia de tattoo","Aguardar"))
... E54: =IF(D54<>"",TODAY()-D54,"") | F54: =IF(E54="","",IF(E54>90,"🔴 ENTRAR EM CONTATO",IF(E54>60,"🟡 VERIFICAR EM BREVE","🟢 OK"))) | G54: =IF(E54>90,"Enviar mensagem no WhatsApp com oferta especial",IF(E54>60,"Perguntar sobre nova ideia de tattoo","Aguardar"))

Sheet 💰 Financeiro
B2: 💰 FINANCEIRO PRO — CENTRAL TATTOO
B5: FATURAMENTO BRUTO | H5: =SUMIF(C10:C200,"Receita",D10:D200)
B6: (-) DESPESAS TOTAIS | H6: =SUMIF(C10:C200,"Despesa",D10:D200)
B7: (=) LUCRO LÍQUIDO | H7: =B5-B6
B8: MARGEM DE LUCRO | H8: =IFERROR(B7/B5,0)
B9: CUSTO POR SESSÃO | H9: =IFERROR(B6/COUNTA(Agenda!B5:B104),0)
B11: 📋 LANÇAMENTOS FINANCEIROS
B12: DATA | C12: DESCRIÇÃO | D12: TIPO | E12: VALOR (R$) | F12: CATEGORIA | G12: FORMA PGTO | H12: REFERÊNCIA | I12: OBS
B122: 📊 DRE — DEMONSTRATIVO DE RESULTADO
B123: (+) RECEITA BRUTA | F123: =SUMIF(C10:C500,"Receita",D10:D500)
B124: (-) Materiais e Insumos | F124: =SUMIF(C10:C500,"Custo Variável",D10:D500)
B125: (-) Comissões | F125: =SUMIF(C10:C500,"Comissão",D10:D500)
B126: (=) LUCRO BRUTO | F126: =F123-F124-F125
B127: (-) Aluguel / Infraestrutura | F127: =SUMIF(C10:C500,"Fixo",D10:D500)
B128: (-) Marketing / Tráfego | F128: =SUMIF(C10:C500,"Marketing",D10:D500)
B129: (-) Outros Fixos | F129: =SUMIF(C10:C500,"Outros",D10:D500)
B130: (=) EBITDA | F130: =F126-F127-F128-F129
B131: (=) LUCRO LÍQUIDO | F131: =F130
B132: (%) Margem Líquida | F132: =IF(F123>0,F131/F123,0)

Sheet 🧮 Calculadora
B2: 🧮 CALCULADORA DE PREÇO PREMIUM
B4: ⚙️ PARÂMETROS DO PROJETO
B5: Horas estimadas de trabalho | H5: 3
B6: Valor da sua hora (R$) | H6: 80
B7: Custo de material (R$) | H7: 50
B8: Tamanho (1=Pequeno, 2=Médio, 3=Grande, 4=Manga) | H8: 2
B9: Complexidade (1=Simples, 2=Médio, 3=Complexo) | H9: 2
B10: Cover Up? (1=Sim, 0=Não) | H10: 0
B11: Colorida? (1=Sim, 0=Não) | H11: 0
B12: Região sensível? (1=Sim, 0=Não) | H12: 0
B13: Margem de lucro desejada % | H13: 40
B15: 💰 RESULTADO DO CÁLCULO
C16: Custo base (horas × hora) | I16: =H5*H6+H7
C17: Multiplicador de tamanho | I17: =IF(H8=1,1,IF(H8=2,1.3,IF(H8=3,1.7,2.5)))
C18: Multiplicador de complexidade | I18: =IF(H9=1,1,IF(H9=2,1.25,1.6))
C19: Adicional cover up (+40%) | I19: =IF(H10=1,B16*0.4,0)
C20: Adicional colorida (+30%) | I20: =IF(H11=1,B16*0.3,0)
C21: Adicional região (+20%) | I21: =IF(H12=1,B16*0.2,0)
C22: Subtotal antes margem | I22: =B16*B17*B18+B19+B20+B21
C23: Margem de lucro | I23: =B22*(H13/100)
C24: ⭐ PREÇO MÍNIMO SUGERIDO | I24: =CEILING(B22+B23,50)
C25: ⭐ PREÇO PREMIUM (+20%) | I25: =CEILING((B22+B23)*1.2,50)
C26: Lucro na venda mínima | I26: =B24-B16
C27: Lucro no preço premium | I27: =B25-B16
B63: 💡 COMPARATIVO DE TICKET — MERCADO BH 2026
B64: NÍVEL | C64: PREÇO/HORA | D64: 3 HORAS | E64: 6 HORAS | F64: 10 HORAS | G64: % MERCADO
B65: Básico | C65: R$ 80-120 | D65: R$ 240-360 | E65: R$ 480-720 | F65: R$ 800-1200 | G65: 40%
B66: Médio | C66: R$ 150-220 | D66: R$ 450-660 | E66: R$ 900-1320 | F66: R$ 1500-2200 | G66: 35%
B67: Premium | C67: R$ 250-380 | D67: R$ 750-1140 | E67: R$ 1500-2280 | F67: R$ 2500-3800 | G67: 20%
B68: Top Artista | C68: R$ 450-700 | D68: R$ 1350-2100 | E68: R$ 2700-4200 | F68: R$ 4500-7000 | G68: 5%

Sheet 📦 Estoque
B2: 📦 CONTROLE DE ESTOQUE — CENTRAL TATTOO
B4: MATERIAL | C4: CATEGORIA | D4: QTD ATUAL | E4: UNID. | F4: CUSTO UNIT. | G4: VALOR TOTAL | H4: QTD MÍNIMA | I4: STATUS | J4: ÚLTIMO PEDIDO | K4: FORNECEDOR | L4: CUSTO/SESSÃO | M4: REPOSIÇÃO?
B5: Tinta Preta | C5: Tinta | D5: 5 | E5: frascos | F5: =IF(AND(C5<>"",E5<>""),C5*E5,"") | G5: =C5*E5 | H5: =IF(C5="","",IF(C5<=G5,"🔴 REPOR JÁ",IF(C5<=G5*1.5,"🟡 ATENÇÃO","🟢 OK"))) | I5: =IF(C5<=G5,"🔴 REPOR JÁ",IF(C5<=G5*1.5,"🟡 ATENÇÃO","🟢 OK")) | L5: =IF(C5>0,E5/C5,"") | M5: =IF(C5<>"",IF(C5<=G5,"⚠️ PEDIDO URGENTE",IF(C5<=G5*1.5,"📦 Planejar Pedido","✅ Estoque OK")),"")
B6: Tinta Colorida Vermelha | C6: Tinta | D6: 3 | E6: frascos | F6: =IF(AND(C6<>"",E6<>""),C6*E6,"") | G6: =C6*E6 | H6: =IF(C6="","",IF(C6<=G6,"🔴 REPOR JÁ",IF(C6<=G6*1.5,"🟡 ATENÇÃO","🟢 OK"))) | I6: =IF(C6<=G6,"🔴 REPOR JÁ",IF(C6<=G6*1.5,"🟡 ATENÇÃO","🟢 OK")) | L6: =IF(C6>0,E6/C6,"") | M6: =IF(C6<>"",IF(C6<=G6,"⚠️ PEDIDO URGENTE",IF(C6<=G6*1.5,"📦 Planejar Pedido","✅ Estoque OK")),"")
B7: Tinta Colorida Azul | C7: Tinta | D7: 3 | E7: frascos | F7: =IF(AND(C7<>"",E7<>""),C7*E7,"") | G7: =C7*E7 | H7: =IF(C7="","",IF(C7<=G7,"🔴 REPOR JÁ",IF(C7<=G7*1.5,"🟡 ATENÇÃO","🟢 OK"))) | I7: =IF(C7<=G7,"🔴 REPOR JÁ",IF(C7<=G7*1.5,"🟡 ATENÇÃO","🟢 OK")) | L7: =IF(C7>0,E7/C7,"") | M7: =IF(C7<>"",IF(C7<=G7,"⚠️ PEDIDO URGENTE",IF(C7<=G7*1.5,"📦 Planejar Pedido","✅ Estoque OK")),"")
B8: Agulhas Liner 3RL | C8: Agulhas | D8: 50 | E8: un | F8: =IF(AND(C8<>"",E8<>""),C8*E8,"") | G8: =C8*E8 | H8: =IF(C8="","",IF(C8<=G8,"🔴 REPOR JÁ",IF(C8<=G8*1.5,"🟡 ATENÇÃO","🟢 OK"))) | I8: =IF(C8<=G8,"🔴 REPOR JÁ",IF(C8<=G8*1.5,"🟡 ATENÇÃO","🟢 OK")) | L8: =IF(C8>0,E8/C8,"") | M8: =IF(C8<>"",IF(C8<=G8,"⚠️ PEDIDO URGENTE",IF(C8<=G8*1.5,"📦 Planejar Pedido","✅ Estoque OK")),"")
B9: Agulhas Liner 5RL | C9: Agulhas | D9: 50 | E9: un | F9: =IF(AND(C9<>"",E9<>""),C9*E9,"") | G9: =C9*E9 | H9: =IF(C9="","",IF(C9<=G9,"🔴 REPOR JÁ",IF(C9<=G9*1.5,"🟡 ATENÇÃO","🟢 OK"))) | I9: =IF(C9<=G9,"🔴 REPOR JÁ",IF(C9<=G9*1.5,"🟡 ATENÇÃO","🟢 OK")) | L9: =IF(C9>0,E9/C9,"") | M9: =IF(C9<>"",IF(C9<=G9,"⚠️ PEDIDO URGENTE",IF(C9<=G9*1.5,"📦 Planejar Pedido","✅ Estoque OK")),"")
B10: Agulhas Shader 7M | C10: Agulhas | D10: 30 | E10: un | F10: =IF(AND(C10<>"",E10<>""),C10*E10,"") | G10: =C10*E10 | H10: =IF(C10="","",IF(C10<=G10,"🔴 REPOR JÁ",IF(C10<=G10*1.5,"🟡 ATENÇÃO","🟢 OK"))) | I10: =IF(C10<=G10,"🔴 REPOR JÁ",IF(C10<=G10*1.5,"🟡 ATENÇÃO","🟢 OK")) | L10: =IF(C10>0,E10/C10,"") | M10: =IF(C10<>"",IF(C10<=G10,"⚠️ PEDIDO URGENTE",IF(C10<=G10*1.5,"📦 Planejar Pedido","✅ Estoque OK")),"")
B11: Agulhas Magnum 15M | C11: Agulhas | D11: 20 | E11: un | F11: =IF(AND(C11<>"",E11<>""),C11*E11,"") | G11: =C11*E11 | H11: =IF(C11="","",IF(C11<=G11,"🔴 REPOR JÁ",IF(C11<=G11*1.5,"🟡 ATENÇÃO","🟢 OK"))) | I11: =IF(C11<=G11,"🔴 REPOR JÁ",IF(C11<=G11*1.5,"🟡 ATENÇÃO","🟢 OK")) | L11: =IF(C11>0,E11/C11,"") | M11: =IF(C11<>"",IF(C11<=G11,"⚠️ PEDIDO URGENTE",IF(C11<=G11*1.5,"📦 Planejar Pedido","✅ Estoque OK")),"")
B12: Película de Proteção | C12: Proteção | D12: 100 | E12: metros | F12: =IF(AND(C12<>"",E12<>""),C12*E12,"") | G12: =C12*E12 | H12: =IF(C12="","",IF(C12<=G12,"🔴 REPOR JÁ",IF(C12<=G12*1.5,"🟡 ATENÇÃO","🟢 OK"))) | I12: =IF(C12<=G12,"🔴 REPOR JÁ",IF(C12<=G12*1.5,"🟡 ATENÇÃO","🟢 OK")) | L12: =IF(C12>0,E12/C12,"") | M12: =IF(C12<>"",IF(C12<=G12,"⚠️ PEDIDO URGENTE",IF(C12<=G12*1.5,"📦 Planejar Pedido","✅ Estoque OK")),"")
B13: Luvas Nitrila P | C13: Segurança | D13: 2 | E13: caixas | F13: =IF(AND(C13<>"",E13<>""),C13*E13,"") | G13: =C13*E13 | H13: =IF(C13="","",IF(C13<=G13,"🔴 REPOR JÁ",IF(C13<=G13*1.5,"🟡 ATENÇÃO","🟢 OK"))) | I13: =IF(C13<=G13,"🔴 REPOR JÁ",IF(C13<=G13*1.5,"🟡 ATENÇÃO","🟢 OK")) | L13: =IF(C13>0,E13/C13,"") | M13: =IF(C13<>"",IF(C13<=G13,"⚠️ PEDIDO URGENTE",IF(C13<=G13*1.5,"📦 Planejar Pedido","✅ Estoque OK")),"")
B14: Luvas Nitrila M | C14: Segurança | D14: 2 | E14: caixas | F14: =IF(AND(C14<>"",E14<>""),C14*E14,"") | G14: =C14*E14 | H14: =IF(C14="","",IF(C14<=G14,"🔴 REPOR JÁ",IF(C14<=G14*1.5,"🟡 ATENÇÃO","🟢 OK"))) | I14: =IF(C14<=G14,"🔴 REPOR JÁ",IF(C14<=G14*1.5,"🟡 ATENÇÃO","🟢 OK")) | L14: =IF(C14>0,E14/C14,"") | M14: =IF(C14<>"",IF(C14<=G14,"⚠️ PEDIDO URGENTE",IF(C14<=G14*1.5,"📦 Planejar Pedido","✅ Estoque OK")),"")
B15: Luvas Nitrila G | C15: Segurança | D15: 1 | E15: caixas | F15: =IF(AND(C15<>"",E15<>""),C15*E15,"") | G15: =C15*E15 | H15: =IF(C15="","",IF(C15<=G15,"🔴 REPOR JÁ",IF(C15<=G15*1.5,"🟡 ATENÇÃO","🟢 OK"))) | I15: =IF(C15<=G15,"🔴 REPOR JÁ",IF(C15<=G15*1.5,"🟡 ATENÇÃO","🟢 OK")) | L15: =IF(C15>0,E15/C15,"") | M15: =IF(C15<>"",IF(C15<=G15,"⚠️ PEDIDO URGENTE",IF(C15<=G15*1.5,"📦 Planejar Pedido","✅ Estoque OK")),"")
B16: Vaselina | C16: Consumível | D16: 10 | E16: potes | F16: =IF(AND(C16<>"",E16<>""),C16*E16,"") | G16: =C16*E16 | H16: =IF(C16="","",IF(C16<=G16,"🔴 REPOR JÁ",IF(C16<=G16*1.5,"🟡 ATENÇÃO","🟢 OK"))) | I16: =IF(C16<=G16,"🔴 REPOR JÁ",IF(C16<=G16*1.5,"🟡 ATENÇÃO","🟢 OK")) | L16: =IF(C16>0,E16/C16,"") | M16: =IF(C16<>"",IF(C16<=G16,"⚠️ PEDIDO URGENTE",IF(C16<=G16*1.5,"📦 Planejar Pedido","✅ Estoque OK")),"")
... B24: Papel Hectográfico | C24: Consumível | D24: 100 | E24: folhas | F24: =IF(AND(C24<>"",E24<>""),C24*E24,"") | G24: =C24*E24 | H24: =IF(C24="","",IF(C24<=G24,"🔴 REPOR JÁ",IF(C24<=G24*1.5,"🟡 ATENÇÃO","🟢 OK"))) | I24: =IF(C24<=G24,"🔴 REPOR JÁ",IF(C24<=G24*1.5,"🟡 ATENÇÃO","🟢 OK")) | L24: =IF(C24>0,E24/C24,"") | M24: =IF(C24<>"",IF(C24<=G24,"⚠️ PEDIDO URGENTE",IF(C24<=G24*1.5,"📦 Planejar Pedido","✅ Estoque OK")),"")
F25: =IF(AND(C25<>"",E25<>""),C25*E25,"") | H25: =IF(C25="","",IF(C25<=G25,"🔴 REPOR JÁ",IF(C25<=G25*1.5,"🟡 ATENÇÃO","🟢 OK"))) | L25: =IF(C25>0,E25/C25,"") | M25: =IF(C25<>"",IF(C25<=G25,"⚠️ PEDIDO URGENTE",IF(C25<=G25*1.5,"📦 Planejar Pedido","✅ Estoque OK")),"")
B26: VALOR TOTAL DO ESTOQUE | F26: =IF(AND(C26<>"",E26<>""),C26*E26,"") | H26: =IF(C26="","",IF(C26<=G26,"🔴 REPOR JÁ",IF(C26<=G26*1.5,"🟡 ATENÇÃO","🟢 OK"))) | L26: =IF(C26>0,E26/C26,"") | M26: =IF(C26<>"",IF(C26<=G26,"⚠️ PEDIDO URGENTE",IF(C26<=G26*1.5,"📦 Planejar Pedido","✅ Estoque OK")),"")
F27: =IF(AND(C27<>"",E27<>""),C27*E27,"") | H27: =IF(C27="","",IF(C27<=G27,"🔴 REPOR JÁ",IF(C27<=G27*1.5,"🟡 ATENÇÃO","🟢 OK"))) | L27: =IF(C27>0,E27/C27,"") | M27: =IF(C27<>"",IF(C27<=G27,"⚠️ PEDIDO URGENTE",IF(C27<=G27*1.5,"📦 Planejar Pedido","✅ Estoque OK")),"")
F28: =IF(AND(C28<>"",E28<>""),C28*E28,"") | H28: =IF(C28="","",IF(C28<=G28,"🔴 REPOR JÁ",IF(C28<=G28*1.5,"🟡 ATENÇÃO","🟢 OK"))) | L28: =IF(C28>0,E28/C28,"") | M28: =IF(C28<>"",IF(C28<=G28,"⚠️ PEDIDO URGENTE",IF(C28<=G28*1.5,"📦 Planejar Pedido","✅ Estoque OK")),"")
F29: =IF(AND(C29<>"",E29<>""),C29*E29,"") | H29: =IF(C29="","",IF(C29<=G29,"🔴 REPOR JÁ",IF(C29<=G29*1.5,"🟡 ATENÇÃO","🟢 OK"))) | L29: =IF(C29>0,E29/C29,"") | M29: =IF(C29<>"",IF(C29<=G29,"⚠️ PEDIDO URGENTE",IF(C29<=G29*1.5,"📦 Planejar Pedido","✅ Estoque OK")),"")
F30: =IF(AND(C30<>"",E30<>""),C30*E30,"") | H30: =IF(C30="","",IF(C30<=G30,"🔴 REPOR JÁ",IF(C30<=G30*1.5,"🟡 ATENÇÃO","🟢 OK"))) | L30: =IF(C30>0,E30/C30,"") | M30: =IF(C30<>"",IF(C30<=G30,"⚠️ PEDIDO URGENTE",IF(C30<=G30*1.5,"📦 Planejar Pedido","✅ Estoque OK")),"")
F31: =IF(AND(C31<>"",E31<>""),C31*E31,"") | H31: =IF(C31="","",IF(C31<=G31,"🔴 REPOR JÁ",IF(C31<=G31*1.5,"🟡 ATENÇÃO","🟢 OK"))) | L31: =IF(C31>0,E31/C31,"") | M31: =IF(C31<>"",IF(C31<=G31,"⚠️ PEDIDO URGENTE",IF(C31<=G31*1.5,"📦 Planejar Pedido","✅ Estoque OK")),"")
F32: =IF(AND(C32<>"",E32<>""),C32*E32,"") | H32: =IF(C32="","",IF(C32<=G32,"🔴 REPOR JÁ",IF(C32<=G32*1.5,"🟡 ATENÇÃO","🟢 OK"))) | L32: =IF(C32>0,E32/C32,"") | M32: =IF(C32<>"",IF(C32<=G32,"⚠️ PEDIDO URGENTE",IF(C32<=G32*1.5,"📦 Planejar Pedido","✅ Estoque OK")),"")
F33: =IF(AND(C33<>"",E33<>""),C33*E33,"") | H33: =IF(C33="","",IF(C33<=G33,"🔴 REPOR JÁ",IF(C33<=G33*1.5,"🟡 ATENÇÃO","🟢 OK"))) | L33: =IF(C33>0,E33/C33,"") | M33: =IF(C33<>"",IF(C33<=G33,"⚠️ PEDIDO URGENTE",IF(C33<=G33*1.5,"📦 Planejar Pedido","✅ Estoque OK")),"")
F34: =IF(AND(C34<>"",E34<>""),C34*E34,"") | H34: =IF(C34="","",IF(C34<=G34,"🔴 REPOR JÁ",IF(C34<=G34*1.5,"🟡 ATENÇÃO","🟢 OK"))) | L34: =IF(C34>0,E34/C34,"") | M34: =IF(C34<>"",IF(C34<=G34,"⚠️ PEDIDO URGENTE",IF(C34<=G34*1.5,"📦 Planejar Pedido","✅ Estoque OK")),"")
F35: =IF(AND(C35<>"",E35<>""),C35*E35,"") | H35: =IF(C35="","",IF(C35<=G35,"🔴 REPOR JÁ",IF(C35<=G35*1.5,"🟡 ATENÇÃO","🟢 OK"))) | L35: =IF(C35>0,E35/C35,"") | M35: =IF(C35<>"",IF(C35<=G35,"⚠️ PEDIDO URGENTE",IF(C35<=G35*1.5,"📦 Planejar Pedido","✅ Estoque OK")),"")
F36: =IF(AND(C36<>"",E36<>""),C36*E36,"") | H36: =IF(C36="","",IF(C36<=G36,"🔴 REPOR JÁ",IF(C36<=G36*1.5,"🟡 ATENÇÃO","🟢 OK"))) | L36: =IF(C36>0,E36/C36,"") | M36: =IF(C36<>"",IF(C36<=G36,"⚠️ PEDIDO URGENTE",IF(C36<=G36*1.5,"📦 Planejar Pedido","✅ Estoque OK")),"")
F37: =IF(AND(C37<>"",E37<>""),C37*E37,"") | H37: =IF(C37="","",IF(C37<=G37,"🔴 REPOR JÁ",IF(C37<=G37*1.5,"🟡 ATENÇÃO","🟢 OK"))) | L37: =IF(C37>0,E37/C37,"") | M37: =IF(C37<>"",IF(C37<=G37,"⚠️ PEDIDO URGENTE",IF(C37<=G37*1.5,"📦 Planejar Pedido","✅ Estoque OK")),"")
F38: =IF(AND(C38<>"",E38<>""),C38*E38,"") | H38: =IF(C38="","",IF(C38<=G38,"🔴 REPOR JÁ",IF(C38<=G38*1.5,"🟡 ATENÇÃO","🟢 OK"))) | L38: =IF(C38>0,E38/C38,"") | M38: =IF(C38<>"",IF(C38<=G38,"⚠️ PEDIDO URGENTE",IF(C38<=G38*1.5,"📦 Planejar Pedido","✅ Estoque OK")),"")
... F200: =IF(AND(C200<>"",E200<>""),C200*E200,"") | H200: =IF(C200="","",IF(C200<=G200,"🔴 REPOR JÁ",IF(C200<=G200*1.5,"🟡 ATENÇÃO","🟢 OK"))) | L200: =IF(C200>0,E200/C200,"") | M200: =IF(C200<>"",IF(C200<=G200,"⚠️ PEDIDO URGENTE",IF(C200<=G200*1.5,"📦 Planejar Pedido","✅ Estoque OK")),"")

Sheet 🎯 Leads
B2: 🎯 PIPELINE DE LEADS — CENTRAL TATTOO
B4: TOTAL LEADS | E4: ORÇAMENTOS | H4: CONFIRMADOS | K4: PERDIDOS
B5: =COUNTA(B9:B108) | E5: =COUNTIF(F9:F208,"*Perdido*") | H5: =COUNTIF(F9:F108,"Confirmado") | K5: =COUNTIF(F9:F108,"Perdido")
B8: NOME | C8: TELEFONE | D8: ORIGEM | E8: DATA ENTRADA | F8: ESTILO INTERESSE | G8: TEMPERATURA | H8: VALOR ESTIMADO | I8: PRÓX. AÇÃO | J8: RESPONSÁVEL | K8: DATA FOLLOW | L8: OBS

Sheet 📈 Metas
B2: 📈 METAS E PREVISÃO DE FATURAMENTO — CENTRAL TATTOO
B4: 🎯 QUANTO PRECISO TATUAR POR MÊS?
B5: Meta de faturamento mensal (R$) | H5: 5000
B6: Horas disponíveis por dia | H6: 8
B7: Dias trabalhados por mês | H7: 22
B8: Ticket médio por sessão (R$) | H8: 600
B9: Taxa de conversão de leads (%) | H9: 30
B11: 📊 RESULTADOS
B12: Sessões necessárias/mês | H12: =CEILING(B5/B8,1)
B13: Horas de trabalho/dia necessárias | H13: =IFERROR((B9*B8)/(B8*B6),0)
B14: Leads necessários p/ atingir meta | H14: =CEILING(B9/B7,1)
B15: Faturamento possível (cheio) | H15: =B6*B7*B8
B16: Folga de capacidade | H16: =B15-B5
B19: 📅 PROJEÇÃO 12 MESES
B20: MÉTRICA | C20: Jan | D20: Fev | E20: Mar | F20: Abr | G20: Mai | H20: Jun | I20: Jul | J20: Ago | K20: Set | L20: Out | M20: Nov | N20: Dez
B21: Meta (R$)
B22: Realizado (R$)
B23: Atingido (%)
B24: Sessões Planej.
B25: Sessões Reais
B83: 📅 ACOMPANHAMENTO MENSAL 2026
B84: INDICADOR | C84: JAN | D84: FEV | E84: MAR | F84: ABR | G84: MAI | H84: JUN | I84: JUL | J84: AGO | K84: SET | L84: OUT | M84: NOV | N84: DEZ | O84: TOTAL/MÉD
B85: Meta Fat. (R$) | C85: 8000 | D85: 8000 | E85: 8000 | F85: 8000 | G85: 8000 | H85: 8000 | I85: 8000 | J85: 8000 | K85: 8000 | L85: 8000 | M85: 8000 | N85: 8000 | O85: =SUM(C85:N85)
B86: Real Fat. (R$) | C86: 0 | D86: 0 | E86: 0 | F86: 0 | G86: 0 | H86: 0 | I86: 0 | J86: 0 | K86: 0 | L86: 0 | M86: 0 | N86: 0 | O86: =SUM(C86:N86)
B87: % Ating. | C87: =IF(C86>0,C86/C85,0) | D87: =IF(D86>0,D86/D85,0) | E87: =IF(E86>0,E86/E85,0) | F87: =IF(F86>0,F86/F85,0) | G87: =IF(G86>0,G86/G85,0) | H87: =IF(H86>0,H86/H85,0) | I87: =IF(I86>0,I86/I85,0) | J87: =IF(J86>0,J86/J85,0) | ... N87: =IF(N86>0,N86/N85,0) | O87: =AVERAGE(C87:N87)
B88: Meta Sessões | C88: 20 | D88: 20 | E88: 20 | F88: 20 | G88: 20 | H88: 20 | I88: 20 | J88: 20 | K88: 20 | L88: 20 | M88: 20 | N88: 20 | O88: =SUM(C88:N88)
B89: Real Sessões | C89: 0 | D89: 0 | E89: 0 | F89: 0 | G89: 0 | H89: 0 | I89: 0 | J89: 0 | K89: 0 | L89: 0 | M89: 0 | N89: 0 | O89: =SUM(C89:N89)
B90: Ticket Médio Real | C90: =IF(C89>0,C86/C89,"") | D90: =IF(D89>0,D86/D89,"") | E90: =IF(E89>0,E86/E89,"") | F90: =IF(F89>0,F86/F89,"") | G90: =IF(G89>0,G86/G89,"") | H90: =IF(H89>0,H86/H89,"") | I90: =IF(I89>0,I86/I89,"") | J90: =IF(J89>0,J86/J89,"") | ... N90: =IF(N89>0,N86/N89,"") | O90: =SUM(C90:N90)

Sheet 💎 Sinais
B2: 💎 CONTROLE DE SINAIS E PAGAMENTOS
B3: AGUARDANDO | E3: RECEBIDOS | H3: ATRASADOS | K3: TOTAL SINAIS
B4: =COUNTIF(I5:I104,"Pendente") | E4: =COUNTIF(I5:I104,"Pago") | H4: =COUNTIF(I5:I104,"Atrasado") | K4: =SUM(F5:F104)
B5: CLIENTE | C5: DATA SESSÃO | D5: DATA VENCIM. | E5: ESTILO | F5: VALOR TOTAL | G5: SINAL COBRADO | H5: SALDO | I5: DATA PAGTO | J5: STATUS | K5: OBSERVAÇÕES
H6: =IF(F6<>"",F6-G6,"")
H7: =IF(F7<>"",F7-G7,"")
H8: =IF(F8<>"",F8-G8,"")
H9: =IF(F9<>"",F9-G9,"")
H10: =IF(F10<>"",F10-G10,"")
H11: =IF(F11<>"",F11-G11,"")
H12: =IF(F12<>"",F12-G12,"")
H13: =IF(F13<>"",F13-G13,"")
H14: =IF(F14<>"",F14-G14,"")
H15: =IF(F15<>"",F15-G15,"")
H16: =IF(F16<>"",F16-G16,"")
H17: =IF(F17<>"",F17-G17,"")
... H105: =IF(F105<>"",F105-G105,"")

Sheet 🌿 Cicatrização
B2: 🌿 CONTROLE DE CICATRIZAÇÃO E RETORNO
B4: CLIENTE | C4: TELEFONE | D4: DATA SESSÃO | E4: ESTILO | F4: REGIÃO | G4: RETORNO (30d) | H4: CICATRIZAÇÃO | I4: RETOQUE GRÁTIS? | J4: DATA RETOQUE | K4: AVALIAÇÃO | L4: OBS
G5: =IF(D5<>"",D5+30,"") | H5: =IF(G5="","",IF(TODAY()>G5+15,"✅ Cicatrizou","⏳ Em processo"))
G6: =IF(D6<>"",D6+30,"") | H6: =IF(G6="","",IF(TODAY()>G6+15,"✅ Cicatrizou","⏳ Em processo"))
G7: =IF(D7<>"",D7+30,"") | H7: =IF(G7="","",IF(TODAY()>G7+15,"✅ Cicatrizou","⏳ Em processo"))
G8: =IF(D8<>"",D8+30,"") | H8: =IF(G8="","",IF(TODAY()>G8+15,"✅ Cicatrizou","⏳ Em processo"))
G9: =IF(D9<>"",D9+30,"") | H9: =IF(G9="","",IF(TODAY()>G9+15,"✅ Cicatrizou","⏳ Em processo"))
G10: =IF(D10<>"",D10+30,"") | H10: =IF(G10="","",IF(TODAY()>G10+15,"✅ Cicatrizou","⏳ Em processo"))
G11: =IF(D11<>"",D11+30,"") | H11: =IF(G11="","",IF(TODAY()>G11+15,"✅ Cicatrizou","⏳ Em processo"))
G12: =IF(D12<>"",D12+30,"") | H12: =IF(G12="","",IF(TODAY()>G12+15,"✅ Cicatrizou","⏳ Em processo"))
G13: =IF(D13<>"",D13+30,"") | H13: =IF(G13="","",IF(TODAY()>G13+15,"✅ Cicatrizou","⏳ Em processo"))
G14: =IF(D14<>"",D14+30,"") | H14: =IF(G14="","",IF(TODAY()>G14+15,"✅ Cicatrizou","⏳ Em processo"))
G15: =IF(D15<>"",D15+30,"") | H15: =IF(G15="","",IF(TODAY()>G15+15,"✅ Cicatrizou","⏳ Em processo"))
G16: =IF(D16<>"",D16+30,"") | H16: =IF(G16="","",IF(TODAY()>G16+15,"✅ Cicatrizou","⏳ Em processo"))
... G104: =IF(D104<>"",D104+30,"") | H104: =IF(G104="","",IF(TODAY()>G104+15,"✅ Cicatrizou","⏳ Em processo"))

Sheet 💼 Comissões
B2: 💼 CONTROLE DE COMISSÕES — CENTRAL TATTOO
B4: ⚙️ TABELA DE COMISSÕES POR PROFISSIONAL
B5: PROFISSIONAL | C5: FUNÇÃO | D5: % COMISSÃO
B6: Carlos Henrique | C6: Tatuador Principal | D6: 0.6
B7: Profissional 2 | C7: Tatuador | D7: 0.55
B8: Recepcionista | C8: Atendimento | D8: 0.3
B9: Body Piercer | C9: Piercing | D9: 0.5
B12: 📋 LANÇAMENTOS DE COMISSÃO
B13: DATA | C13: PROFISSIONAL | D13: SERVIÇO | E13: VALOR SERVIÇO | F13: % COMISSÃO | G13: VALOR COMISSÃO | H13: STATUS PGTO | I13: DATA PGTO
G14: =IF(E14<>"",E14*F14,"")
G15: =IF(E15<>"",E15*F15,"")
G16: =IF(E16<>"",E16*F16,"")
G17: =IF(E17<>"",E17*F17,"")
G18: =IF(E18<>"",E18*F18,"")
G19: =IF(E19<>"",E19*F19,"")
G20: =IF(E20<>"",E20*F20,"")
G21: =IF(E21<>"",E21*F21,"")
G22: =IF(E22<>"",E22*F22,"")
G23: =IF(E23<>"",E23*F23,"")
G24: =IF(E24<>"",E24*F24,"")
G25: =IF(E25<>"",E25*F25,"")
... G63: =IF(E63<>"",E63*F63,"")

Sheet 📋 Contratos
A1: 📋 CONTRATOS & TERMOS DE RESPONSABILIDADE — CENTRAL TATTOO
A3: # | B3: CLIENTE | C3: DATA CONTRATO | D3: DATA SESSÃO | E3: SERVIÇO / DESCRIÇÃO | F3: REGIÃO DO CORPO | G3: VALOR TOTAL | H3: SINAL (R$) | I3: RESTANTE | J3: ASSINADO? | K3: PGTO | L3: FOTO CONSENT. | M3: ALERGIAS / OBS MÉDICAS
A4: =IF(B4<>"",ROW()-3,"") | I4: =IF(AND(G4<>"",H4<>""),G4-H4,"")
A5: =IF(B5<>"",ROW()-3,"") | I5: =IF(AND(G5<>"",H5<>""),G5-H5,"")
A6: =IF(B6<>"",ROW()-3,"") | I6: =IF(AND(G6<>"",H6<>""),G6-H6,"")
A7: =IF(B7<>"",ROW()-3,"") | I7: =IF(AND(G7<>"",H7<>""),G7-H7,"")
A8: =IF(B8<>"",ROW()-3,"") | I8: =IF(AND(G8<>"",H8<>""),G8-H8,"")
A9: =IF(B9<>"",ROW()-3,"") | I9: =IF(AND(G9<>"",H9<>""),G9-H9,"")
A10: =IF(B10<>"",ROW()-3,"") | I10: =IF(AND(G10<>"",H10<>""),G10-H10,"")
A11: =IF(B11<>"",ROW()-3,"") | I11: =IF(AND(G11<>"",H11<>""),G11-H11,"")
A12: =IF(B12<>"",ROW()-3,"") | I12: =IF(AND(G12<>"",H12<>""),G12-H12,"")
A13: =IF(B13<>"",ROW()-3,"") | I13: =IF(AND(G13<>"",H13<>""),G13-H13,"")
A14: =IF(B14<>"",ROW()-3,"") | I14: =IF(AND(G14<>"",H14<>""),G14-H14,"")
A15: =IF(B15<>"",ROW()-3,"") | I15: =IF(AND(G15<>"",H15<>""),G15-H15,"")
... A500: =IF(B500<>"",ROW()-3,"") | I500: =IF(AND(G500<>"",H500<>""),G500-H500,"")

Sheet 📊 Relatório
A1: 📊 RELATÓRIO DE PERFORMANCE — CENTRAL TATTOO
A3: 📅 MÊS: | B3: =TEXT(TODAY(),"MMMM / YYYY")
A6: 💰 FATURAMENTO | E6: 📉 DESPESAS | I6: 💎 LUCRO | M6: 🎯 SESSÕES | Q6: 👥 LEADS NOVOS
A7: =SUMIF('📅 Agenda'!F4:F400,"*Concluído*",'📅 Agenda'!G4:G400) | E7: =SUMIF('💰 Financeiro'!C10:C500,"Fixo",'💰 Financeiro'!D10:D500)+SUMIF('💰 Financeiro'!C10:C500,"Custo Variável",'💰 Financeiro'!D10:D500) | I7: =B7-F7 | M7: =COUNTIF('📅 Agenda'!F4:F400,"*Concluído*") | Q7: =COUNTA('🎯 Leads'!B9:B208)
A11: 🏆 TOP ESTILOS DO MÊS
A12: Realismo | C12: =COUNTIF('📅 Agenda'!E4:E400,"Realismo")
A13: Blackwork | C13: =COUNTIF('📅 Agenda'!E4:E400,"Blackwork")
A14: Old School | C14: =COUNTIF('📅 Agenda'!E4:E400,"Old School")
A15: Fineline | C15: =COUNTIF('📅 Agenda'!E4:E400,"Fineline")
A16: Aquarela | C16: =COUNTIF('📅 Agenda'!E4:E400,"Aquarela")
A17: Japonês | C17: =COUNTIF('📅 Agenda'!E4:E400,"Japonês")
A18: Outros | C18: =COUNTIF('📅 Agenda'!E4:E400,"Outros")
A20: 📣 ORIGEM DOS LEADS
A21: Instagram | C21: =COUNTIF('🎯 Leads'!C9:C208,"Instagram")
A22: WhatsApp | C22: =COUNTIF('🎯 Leads'!C9:C208,"WhatsApp")
A23: Indicação | C23: =COUNTIF('🎯 Leads'!C9:C208,"Indicação")
A24: Google | C24: =COUNTIF('🎯 Leads'!C9:C208,"Google")
A25: TikTok | C25: =COUNTIF('🎯 Leads'!C9:C208,"TikTok")

Sheet 🏷️ Preços
A1: 🏷️ TABELA DE PREÇOS POR ESTILO — CENTRAL TATTOO
G2: ⚙️ Valor Hora Base: | I2: 200
A3: ESTILO | B3: PEQUENO (até 5cm) | C3: MÉDIO (5-15cm) | D3: GRANDE (15-25cm) | E3: MANGA/COSTAS | F3: HORA (R$) | G3: MÍNIMO (R$) | H3: RETOQUE | I3: COVER-UP | J3: OBS
A4: Old School | B4: =$I$2*1.0 | C4: =$I$2*2.0 | D4: =$I$2*3.5 | E4: =$I$2*8.0 | F4: =$I$2*1.0 | G4: =$I$2*1.0 | H4: =$I$2*0.5 | I4: =$I$2*2.6
A5: New School | B5: =$I$2*1.2 | C5: =$I$2*2.2 | D5: =$I$2*4.0 | E5: =$I$2*9.0 | F5: =$I$2*1.1 | G5: =$I$2*1.2 | H5: =$I$2*0.5 | I5: =$I$2*2.9
A6: Realismo | B6: =$I$2*1.5 | C6: =$I$2*3.0 | D6: =$I$2*5.0 | E6: =$I$2*12.0 | F6: =$I$2*1.5 | G6: =$I$2*1.5 | H6: =$I$2*0.5 | I6: =$I$2*3.9
A7: Blackwork | B7: =$I$2*1.0 | C7: =$I$2*2.0 | D7: =$I$2*3.5 | E7: =$I$2*8.0 | F7: =$I$2*1.0 | G7: =$I$2*1.0 | H7: =$I$2*0.5 | I7: =$I$2*2.6
A8: Fineline | B8: =$I$2*1.2 | C8: =$I$2*2.5 | D8: =$I$2*4.0 | E8: =$I$2*9.0 | F8: =$I$2*1.2 | G8: =$I$2*1.2 | H8: =$I$2*0.5 | I8: =$I$2*3.2
A9: Aquarela | B9: =$I$2*1.3 | C9: =$I$2*2.8 | D9: =$I$2*4.5 | E9: =$I$2*10.0 | F9: =$I$2*1.3 | G9: =$I$2*1.3 | H9: =$I$2*0.5 | I9: =$I$2*3.6
A10: Tribal | B10: =$I$2*0.8 | C10: =$I$2*1.5 | D10: =$I$2*3.0 | E10: =$I$2*7.0 | F10: =$I$2*0.8 | G10: =$I$2*0.8 | H10: =$I$2*0.5 | I10: =$I$2*2.0
A11: Geométrico | B11: =$I$2*1.0 | C11: =$I$2*2.0 | D11: =$I$2*3.5 | E11: =$I$2*8.0 | F11: =$I$2*1.0 | G11: =$I$2*1.0 | H11: =$I$2*0.5 | I11: =$I$2*2.6
A12: Japonês | B12: =$I$2*1.5 | C12: =$I$2*3.0 | D12: =$I$2*5.0 | E12: =$I$2*14.0 | F12: =$I$2*1.4 | G12: =$I$2*1.5 | H12: =$I$2*0.5 | I12: =$I$2*3.9
A13: Neotradicional | B13: =$I$2*1.3 | C13: =$I$2*2.5 | D13: =$I$2*4.0 | E13: =$I$2*10.0 | F13: =$I$2*1.2 | G13: =$I$2*1.3 | H13: =$I$2*0.5 | I13: =$I$2*3.2
A14: Lettering | B14: =$I$2*0.5 | C14: =$I$2*1.0 | D14: =$I$2*2.0 | E14: =$I$2*5.0 | F14: =$I$2*0.8 | G14: =$I$2*0.5 | H14: =$I$2*0.5 | I14: =$I$2*1.3
A15: Pontilhismo | B15: =$I$2*1.0 | C15: =$I$2*2.0 | D15: =$I$2*3.5 | E15: =$I$2*8.0 | F15: =$I$2*1.0 | G15: =$I$2*1.0 | H15: =$I$2*0.5 | I15: =$I$2*2.6
A16: Cover-Up | B16: =$I$2*1.5 | C16: =$I$2*3.0 | D16: =$I$2*5.0 | E16: =$I$2*12.0 | F16: =$I$2*1.5 | G16: =$I$2*1.5 | H16: =$I$2*0.5 | I16: =$I$2*3.9
A17: Trash Polka | B17: =$I$2*1.3 | C17: =$I$2*2.8 | D17: =$I$2*4.5 | E17: =$I$2*10.0 | F17: =$I$2*1.3 | G17: =$I$2*1.3 | H17: =$I$2*0.5 | I17: =$I$2*3.6
A20: 💡 Para alterar todos os preços automaticamente, mude apenas o valor em "⚙️ Valor Hora Base" (célula I2)

Sheet 📱 Marketing
A1: 📱 CONTROLE DE MARKETING & TRÁFEGO PAGO — CENTRAL TATTOO
A3: MÊS | B3: PLATAFORMA | C3: TIPO CAMPANHA | D3: VERBA (R$) | E3: IMPRESSÕES | F3: CLIQUES | G3: LEADS GERADOS | H3: CONVERTIDOS | I3: FATUR. GERADO | J3: CPL (R$) | K3: CPC (R$) | L3: ROI % | M3: OBS
J4: =IF(AND(D4<>"",G4>0),D4/G4,"") | K4: =IF(AND(D4<>"",F4>0),D4/F4,"") | L4: =IF(AND(I4<>"",D4>0),(I4-D4)/D4,"")
J5: =IF(AND(D5<>"",G5>0),D5/G5,"") | K5: =IF(AND(D5<>"",F5>0),D5/F5,"") | L5: =IF(AND(I5<>"",D5>0),(I5-D5)/D5,"")
J6: =IF(AND(D6<>"",G6>0),D6/G6,"") | K6: =IF(AND(D6<>"",F6>0),D6/F6,"") | L6: =IF(AND(I6<>"",D6>0),(I6-D6)/D6,"")
J7: =IF(AND(D7<>"",G7>0),D7/G7,"") | K7: =IF(AND(D7<>"",F7>0),D7/F7,"") | L7: =IF(AND(I7<>"",D7>0),(I7-D7)/D7,"")
J8: =IF(AND(D8<>"",G8>0),D8/G8,"") | K8: =IF(AND(D8<>"",F8>0),D8/F8,"") | L8: =IF(AND(I8<>"",D8>0),(I8-D8)/D8,"")
J9: =IF(AND(D9<>"",G9>0),D9/G9,"") | K9: =IF(AND(D9<>"",F9>0),D9/F9,"") | L9: =IF(AND(I9<>"",D9>0),(I9-D9)/D9,"")
J10: =IF(AND(D10<>"",G10>0),D10/G10,"") | K10: =IF(AND(D10<>"",F10>0),D10/F10,"") | L10: =IF(AND(I10<>"",D10>0),(I10-D10)/D10,"")
J11: =IF(AND(D11<>"",G11>0),D11/G11,"") | K11: =IF(AND(D11<>"",F11>0),D11/F11,"") | L11: =IF(AND(I11<>"",D11>0),(I11-D11)/D11,"")
J12: =IF(AND(D12<>"",G12>0),D12/G12,"") | K12: =IF(AND(D12<>"",F12>0),D12/F12,"") | L12: =IF(AND(I12<>"",D12>0),(I12-D12)/D12,"")
J13: =IF(AND(D13<>"",G13>0),D13/G13,"") | K13: =IF(AND(D13<>"",F13>0),D13/F13,"") | L13: =IF(AND(I13<>"",D13>0),(I13-D13)/D13,"")
J14: =IF(AND(D14<>"",G14>0),D14/G14,"") | K14: =IF(AND(D14<>"",F14>0),D14/F14,"") | L14: =IF(AND(I14<>"",D14>0),(I14-D14)/D14,"")
J15: =IF(AND(D15<>"",G15>0),D15/G15,"") | K15: =IF(AND(D15<>"",F15>0),D15/F15,"") | L15: =IF(AND(I15<>"",D15>0),(I15-D15)/D15,"")
... J200: =IF(AND(D200<>"",G200>0),D200/G200,"") | K200: =IF(AND(D200<>"",F200>0),D200/F200,"") | L200: =IF(AND(I200<>"",D200>0),(I200-D200)/D200,"")
A202: TOTAL GERAL | D202: =SUM(D4:D200) | E202: =SUM(E4:E200) | F202: =SUM(F4:F200) | G202: =SUM(G4:G200) | H202: =SUM(H4:H200) | I202: =SUM(I4:I200) | L202: =IF(D202>0,(I202-D202)/D202,"")
